pytesseract_cli/__init__.py
pytesseract_cli/main.py
pytesseract_cli-1.2.0.dist-info/METADATA
pytesseract_cli-1.2.0.dist-info/WHEEL
pytesseract_cli-1.2.0.dist-info/entry_points.txt
pytesseract_cli-1.2.0.dist-info/top_level.txt
pytesseract_cli-1.2.0.dist-info/RECORD
