Metadata-Version: 2.1
Name: pytesseract-cli
Version: 1.2.0
Summary: A pytesseract wrapper enabling OCR on images and directories.
Home-page: https://github.com/bradendubois/pytesseract-cli
Author: Braden Dubois
Author-email: braden.dubois@usask.ca
License: UNKNOWN
Keywords: pytesseract tesseract ocr cli
Platform: UNKNOWN
Requires-Dist: pytesseract (>=0.3.7)
Requires-Dist: Pillow (~=8.2.0)
Requires-Dist: pdf2image (~=1.15.1)
